logdoc/__init__.py
logdoc/cli.py
logdoc/logger.py
logdoc/core/__init__.py
logdoc/core/fix_headers.py
logdoc/core/header_injector.py
logdoc/errors/__init__.py
logdoc/errors/logdoc_exceptions.py
logdoc/utils/__init__.py
logdoc/utils/filemeta.py
logdoc-0.1.0.dist-info/METADATA
logdoc-0.1.0.dist-info/WHEEL
logdoc-0.1.0.dist-info/top_level.txt
logdoc-0.1.0.dist-info/RECORD
